LICENSE
README.md
setup.py
singdown/__init__.py
singdown.egg-info/PKG-INFO
singdown.egg-info/SOURCES.txt
singdown.egg-info/dependency_links.txt
singdown.egg-info/entry_points.txt
singdown.egg-info/not-zip-safe
singdown.egg-info/requires.txt
singdown.egg-info/top_level.txt