Metadata-Version: 2.1
Name: singdown
Version: 2023.4.2.1735
Summary: plaintext singing syntax inspired by Markdown
Home-page: https://github.com/wdbm/singdown
Author: Will Breaden Madden
Author-email: wbm@protonmail.ch
License: GPLv3
Requires-Python: >=3.6
License-File: LICENSE
